MANIFEST.in
README.rst
requirements.txt
setup.py
tasks.py
lino_algus/__init__.py
lino_algus/setup_info.py
lino_algus.egg-info/PKG-INFO
lino_algus.egg-info/SOURCES.txt
lino_algus.egg-info/dependency_links.txt
lino_algus.egg-info/requires.txt
lino_algus.egg-info/top_level.txt
lino_algus/lib/__init__.py
lino_algus/lib/algus/__init__.py
lino_algus/lib/algus/help_texts.py
lino_algus/lib/algus/migrate.py
lino_algus/lib/algus/models.py
lino_algus/lib/algus/user_types.py
lino_algus/lib/algus/locale/de/LC_MESSAGES/django.mo
lino_algus/lib/algus/locale/de/LC_MESSAGES/django.po
lino_algus/lib/algus/locale/et/LC_MESSAGES/django.po
lino_algus/lib/algus/locale/fr/LC_MESSAGES/django.po
lino_algus/lib/lets/__init__.py
lino_algus/lib/lets/desktop.py
lino_algus/lib/lets/models.py
lino_algus/lib/users/__init__.py
lino_algus/lib/users/desktop.py
lino_algus/lib/users/models.py
lino_algus/lib/users/fixtures/__init__.py
lino_algus/lib/users/fixtures/demo.py
lino_algus/lib/users/fixtures/demo2.py
lino_algus/lib/users/fixtures/demo_users.py
lino_algus/projects/__init__.py
lino_algus/projects/algus/__init__.py
lino_algus/projects/algus/manage.py
lino_algus/projects/algus/settings/__init__.py
lino_algus/projects/algus/settings/demo.py
lino_algus/projects/algus/settings/doctests.py
lino_algus/projects/algus/settings/memory.py
lino_algus/projects/algus/settings/fixtures/__init__.py
lino_algus/projects/algus/settings/fixtures/demo.py
lino_algus/projects/algus/settings/media/cache/js/lino_000_en.js
lino_algus/projects/algus/tests/__init__.py
lino_algus/projects/algus/tests/test_simple.py
lino_algus/projects/algus/tests/test_webindex.py
tests/__init__.py