Metadata-Version: 1.1
Name: lino-algus
Version: 0.2.0
Summary: A template for new Lino applications
Home-page: http://algus.lino-framework.org/
Author: Luc Saffre
Author-email: luc@lino-framework.org
License: BSD License
Platform: UNKNOWN
Classifier: Programming Language :: Python
Classifier: Programming Language :: Python :: 2
Classifier: Development Status :: 4 - Beta
Classifier: Environment :: Web Environment
Classifier: Framework :: Django
Classifier: Intended Audience :: Developers
Classifier: Intended Audience :: System Administrators
Classifier: Intended Audience :: Information Technology
Classifier: Intended Audience :: Customer Service
Classifier: License :: OSI Approved :: BSD License
Classifier: Operating System :: OS Independent
Classifier: Topic :: Software Development :: Bug Tracking
